tghelper/__init__.py
tghelper/tghelper.py
tghelper-0.1.4.dist-info/LICENSE
tghelper-0.1.4.dist-info/METADATA
tghelper-0.1.4.dist-info/WHEEL
tghelper-0.1.4.dist-info/top_level.txt
tghelper-0.1.4.dist-info/RECORD
