Metadata-Version: 2.1
Name: tghelper
Version: 0.1.4
Summary: Useful tools to work with TigerGraph in Python
Home-page: https://github.com/louisza/tghelper
Download-URL: https://pypi.org/project/tghelper/
Author: Louis Pienaar
Author-email: louisza1000101@gmail.com
License: MIT
Project-URL: Homepage, https://github.com/louisza/tghelper
Project-URL: Documentation, https://tghelper.readthedocs.io/
Project-URL: Bug Tracker, https://github.com/louisza/tghelper/issues
Keywords: TigerGraph
License-File: LICENSE
